mcp_bench/__init__.py
mcp_bench-0.0.1.dist-info/METADATA
mcp_bench-0.0.1.dist-info/WHEEL
mcp_bench-0.0.1.dist-info/top_level.txt
mcp_bench-0.0.1.dist-info/RECORD
