Metadata-Version: 2.4
Name: mcp-bench
Version: 0.0.1
Summary: A package to install mcp-benchmark
Author-email: Xing Han Lù <mcp-benchmark@googlegroups.com>
Classifier: Programming Language :: Python :: 3
Classifier: License :: OSI Approved :: MIT License
Classifier: Operating System :: OS Independent
Requires-Python: >=3.7
Requires-Dist: mcp-benchmark
